tests/commands_test.py
tests/component_test.py
tests/runtime_test.py
tests/test_helper.py
treebeard/__init__.py
treebeard/conf.py
treebeard/helper.py
treebeard/sentry_setup.py
treebeard/util.py
treebeard/version.py
treebeard/version.txt
treebeard/windows_unicode_fix.py
treebeard/buildtime/build.py
treebeard/buildtime/helper.py
treebeard/importchecker/imports.py
treebeard/logs/__init__.py
treebeard/logs/helpers.py
treebeard/notebooks/commands.py
treebeard/notebooks/types.py
treebeard/other/commands.py
treebeard/runtime/helper.py
treebeard/runtime/run.py
treebeard-0.1.0.dist-info/LICENSE
treebeard-0.1.0.dist-info/METADATA
treebeard-0.1.0.dist-info/WHEEL
treebeard-0.1.0.dist-info/entry_points.txt
treebeard-0.1.0.dist-info/top_level.txt
treebeard-0.1.0.dist-info/RECORD
